{
  "YPF": [
    "YPF",
    "YPFD",
    "petrolera estatal",
    "empresa energética",
    "Vaca Muerta"
  ],
  "Banco Galicia": [
    "Banco Galicia",
    "GGAL",
    "Galicia",
    "grupo financiero"
  ],
  "Pampa Energía": [
    "Pampa Energía",
    "PAMP",
    "energética",
    "generadora de electricidad"
  ],
  "Grupo Supervielle": [
    "Grupo Supervielle",
    "SUPV",
    "Supervielle",
    "banco Supervielle"
  ],
  "Transportadora de Gas del Sur": [
    "Transportadora de Gas del Sur",
    "TGSU2",
    "TGS",
    "empresa de gas"
  ],
  "Aluar": [
    "Aluar",
    "ALUA",
    "aluminio",
    "productora de aluminio"
  ],
  "Cablevisión Holding": [
    "Cablevisión",
    "CVH",
    "Grupo Clarín",
    "telecomunicaciones"
  ],
  "Ternium": [
    "Ternium",
    "TXAR",
    "siderurgia",
    "acero",
    "empresa siderúrgica"
  ],
  "Edenor": [
    "Edenor",
    "EDN",
    "distribuidora eléctrica",
    "energía eléctrica"
  ],
  "Telecom Argentina": [
    "Telecom Argentina",
    "TECO2",
    "telecomunicaciones",
    "empresa de telefonía"
  ],
  "Central Puerto": [
    "Central Puerto",
    "CEPU",
    "generación eléctrica",
    "productora de energía"
  ],
  "Banco Macro": [
    "Banco Macro",
    "BMA",
    "Macro"
  ],
  "BBVA Argentina": [
    "BBVA",
    "BBAR",
    "banco BBVA",
    "banco Francés"
  ],
  "ByMA": [
    "ByMA",
    "Bolsas y Mercados Argentinos",
    "mercado de capitales"
  ],
  "Cresud": [
    "Cresud",
    "CRES",
    "agroindustria",
    "campo",
    "empresa agropecuaria"
  ],
  "Mirgor": [
    "Mirgor",
    "MIRG",
    "industria electrónica",
    "automotriz"
  ],
  "IRSA": [
    "IRSA",
    "IRSA",
    "real estate",
    "inmobiliaria argentina"
  ],
  "TGS": [
    "TGS",
    "TGSU2",
    "gasoducto"
  ],
  "Transener": [
    "Transener",
    "TRAN",
    "transporte de electricidad"
  ],
  "Molinos Río de la Plata": [
    "Molinos",
    "MOLI",
    "alimentos",
    "empresa alimenticia"
  ],
  "Loma Negra": [
    "Loma Negra",
    "LOMA",
    "cementera",
    "cemento argentino"
  ]
}